[
{
"type":"item"
 "name":"致密金属块"
 "money":3.5
 "mod":"cm"
},
{
"type":"item"
 "name":"强化合金块"
 "money":80
 "mod":"cm"
},
{
"type":"item"
 "name":"浓缩炸药"
 "money":18
 "mod":"cm"
},
{
"type":"item"
 "name":"浓缩钍燃料"
 "money":12
 "mod":"cm"
},
{
	"type":"item",
	"name":"organosand",
	"money":-1,
	"mod":"bugs",
},
{
	"type":"item",
	"name":"biomass",
	"money":-1,
	"mod":"bugs",
},
{
	"type":"item",
	"name":"ossature",
	"money":-1,
	"mod":"bugs",
},
{
	"type":"item",
	"name":"nickel",
	"money":-1,
	"mod":"bugs",
},
{
	"type":"item",
	"name":"manganese",
	"money":-1,
	"mod":"bugs",
},
{
	"type":"item",
	"name":"crystal",
	"money":-1,
	"mod":"bugs",
},
{
	"type":"item",
	"name":"biomass-steel",
	"money":-1,
	"mod":"bugs",
},
{
	"type":"item",
	"name":"neoplasm-steel",
	"money":-1,
	"mod":"bugs",
},
{
	"type":"item",
	"name":"organosilicon",
	"money":-1,
	"mod":"bugs",
},
{
	"type":"item",
	"name":"methyl-sulfone",
	"money":-1,
	"mod":"bugs",
},
{
	"type":"liquid",
	"name":"venom",
	"money":-1,
	"mod":"bugs",
},
{
	"type":"unit",
	"name":"election",
	"money":-1,
	"mod":"bugs",
},
{
	"type":"unit",
	"name":"atom",
	"money":-1,
	"mod":"bugs",
},
{
	"type":"block",
	"name":"ash",
	"money":-1,
	"mod":"bugs",
},
{
	"type":"block",
	"name":"albus",
	"money":-1,
	"mod":"bugs",
},
{
	"type":"unit",
	"name":"pildelet",
	"money":-1,
	"mod":"bugs",
},
{
	"type":"unit",
	"name":"egg",
	"money":-1,
	"mod":"bugs",
},
{
	"type":"unit",
	"name":"pioneer",
	"money":20,
	"mod":"bugs",
},
{
	"type":"unit",
	"name":"brigadier",
	"money":70,
	"mod":"bugs",
},
{
	"type":"unit",
	"name":"hurricane",
	"money":65,
	"mod":"bugs",
},
{
	"type":"unit",
	"name":"typhoon",
	"money":115,
	"mod":"bugs",
},
{
	"type":"unit",
	"name":"alter",
	"money":85,
	"mod":"bugs",
},
{
	"type":"unit",
	"name":"anatase",
	"money":15,
	"mod":"bugs",
},
{
	"type":"unit",
	"name":"asbestos",
	"money":85,
	"mod":"bugs",
},
{
	"type":"unit",
	"name":"quartz",
	"money":285,
	"mod":"bugs",
},
{
	"type":"unit",
	"name":"floc",
	"money":15,
	"mod":"bugs",
},
{
	"type":"unit",
	"name":"burst",
	"money":8.5,
	"mod":"bugs",
},
{
	"type":"unit",
	"name":"spider",
	"money":10,
	"mod":"bugs",
},
{
	"type":"unit",
	"name":"tarantula",
	"money":60,
	"mod":"bugs",
},
{
	"type":"unit",
	"name":"group",
	"money":225,
	"mod":"bugs",
},
{
	"type":"unit",
	"name":"mosquito",
	"money":10,
	"mod":"bugs",
},
{
	"type":"unit",
	"name":"concuss",
	"money":60,
	"mod":"bugs",
},
{
	"type":"unit",
	"name":"buffer",
	"money":5,
	"mod":"bugs",
},
]
